{
   "description" : "Гарри Каспаров считается одним из сильнейших игроков в истории шахмат, но Крамник победил его в матче на первенство мира, не проиграв ни одной партии! В 2000 году Крамник выиграл матч со счетом 8.5-6.5, а эта победа, вторая в матче, практически обеспечила ему титул чемпиона.",
   "duration" : null,
   "fen" : "2rq1rk1/pb2bppp/1p2Bn2/8/3P4/1QN2N2/PP3PPP/2R1R1K1 b - - 0 15",
   "id" : "e3b9ccb8-3ce1-11ea-b0f3-ed831f545f90",
   "membership" : 10,
   "questions" : [
      "[Event \"Kasparov - Крамник Classical World Cham\"]\r\n[Site \"London ENG\"]\r\n[Date \"2000.10.24\"]\r\n[Round \"10\"]\r\n[White \"Vladimir Крамник\"]\r\n[Black \"Garry Kasparov\"]\r\n[Result \"1-0\"]\r\n[ECO \"E54\"]\r\n[WhiteElo \"2770\"]\r\n[BlackElo \"2849\"]\r\n[SetUp \"1\"]\r\n[FEN \"rnbq1rk1/pp3ppp/4pn2/2pp4/1bPP4/2NBPN2/PP3PPP/R1BQK2R w KQ - 0 7\"]\r\n[PlyCount \"39\"]\r\n[EventDate \"2000.??.??\"]\r\n[Source \"ChessBase\"]\r\n\r\n{Каким ходом Крамник продолжил развитие?} 7. O-O {[%wrong Поищем сильнейший ход.] [%hint Нужно обеспечить безопасность короля.]} (7. cxd5 $5 {Это приемлемый ход, но Крамник решил продолжить развитие. Как он сыграл?}) (7. h3 $2 dxc4 {У черных удобная позиция. Попробуем снова.}) (7. dxc5 $2 dxc4 {У черных удобная позиция. Попробуем снова.}) \r\n7... cxd4 {Здорово! Какой фигурой брать?} 8. exd4 {[%wrong Поищем сильнейший ход.] [%hint Отыграем пешку и выпустим слона с c1.]} (8. Nxd4 $2 dxc4 {У черных хорошая позиция. Попробуем снова.}) \r\n8... dxc4 {Отличный ход! что дальше?} 9.Bxc4 {[%wrong У черных материальный перевес. Попробуем снова.] [%hint Возьмите пешку.]} b6 {Хороший ход! Какую фигуру белым развить сейчас?} 10. Bg5 {[%wrong Поищем сильнейший ход.] [%hint Попробуем развить фигуру так, чтобы связать черного коня.]} (10. Qe2 $5 {Это хороший ход, но Крамник решил вывести слона. Куда?}) (10. Qb3 $5 {Это хороший ход, но Крамник решил вывести слона. Куда?}) (10. Ne5 $5 {Это хороший ход, но Крамник решил вывести слона. Куда?}) (10. Be3 $2 {Поищем более активное поле для слона.}) (10. Bf4 $2 {Поищем более активное поле для слона.}) (10. d5 $2 Qc7 {У черных хорошая позиция. Попробуем снова.}) (10. Re1 $5 {Этот ход возможен, но Крамник решил сначала развить слона c1. Какой ход он сделал?}) \r\n10... Bb7 {Блестяще! Как белым продолжить развитие фигур?} 11. Re1 {[%wrong Поищем сильнейший ход.] [%hint Развиваемся и занимаем полуоткрытую вертикаль.]} (11. Ne5 $5 {Это хороший ход, но Крамник решил продолжить развитие. Как он сыграл?}) (11. Qe2 $5 {Это хороший ход, но Крамник хочет сначала развить ладьи, а потом - ферзя. Как он сыграл?}) (11. Rc1 $5 {Это хороший ход, но Крамник начал с развития другой ладьи. Как он сыграл?}) \r\n11... Nbd7 {Отличный ход! Как продолжить развитие?} 12. Rc1 {[%wrong Поищем сильнейший ход.] [%hint Займем единственную открытую вертикаль.]} (12. Qb3 $5 {Это хороший ход, но Крамник сначала развил ладью a1. Каким ходом?}) (12. Bd3 $5 {Это хороший ход, но Крамник сначала развил ладью a1. Каким ходом?}) \r\n12... Rc8 {Изумительно! Как защитить слона и создать встречную угрозу?} 13. Qb3 {[%wrong Поищем сильнейший ход. ] [%hint Надо защитить своего слона и напасть на слона черных.]} (13. Bd3 $5 {Это разумный ход, но Крамник решил продолжить развитие и защитить слона. Каким ходом? }) (13. Qe2 $5 {Это хороший ход, но Крамник находит более активное поле для ферзя. Какое?}) (13. Bb3 $2 h6 {У черных безопасная позиция. Попробуйте снова.}) \r\n13... Be7 {Невероятно! Теперь Крамник наносит комбинационный удар и получает материальный перевес. Каким ходом?} 14. Bxf6 {[%wrong Поищем сильнейший ход.] [%hint Поищем полезный размен прежде, чем нанести удар.]} (14. Ne5 $5 {Это сильный ход, но Крамник нашел комбинацию. Какую?}) (14. Bf4 $5 {Это разумный ход, но есть и лучший. Какой ход сделал Крамник?}) (14. Bxe6 $2 fxe6 {Черные после Фxe6 могут ответить Лf7. Поищем полезный размен перед взятием на e6.}) \r\n14... Nxf6 {Молодец! Какой удар, позволяющий получить материальный перевес, нанесли белые?} 15. Bxe6 {[%wrong У черных все в порядке. Попробуем снова.] [%hint Поищем временную жертву фигуры.]} (15. Ne2 $2 Qd6 {Белые сохраняют материальное равенство, но у черных хорошая позиция. Поищем сильнейший ход.}) (15. d5 $2 exd5 {У черных преимущество. Попробуем снова.}) (15. Rxe6 $2 Bxf3 {Черные получают материальное преимущество. Попробуем снова.}) \r\n15... fxe6 {Отличный ход! Какой фигурой брать?} 16. Qxe6+ {[%wrong Поищем сильнейший ход.] [%hint Нападем на короля и слона черных одновременно.]} Kh8 {Изумительно! Как отыграть фигуру?} 17. Qxe7 {[%wrong У черных преимущество. Попробуем снова.] [%hint Как взять фигуру противника?]} (17. Ng5 $2 Rc7 {У черных преимущество. Попробуем снова.}) \r\n17... Bxf3 {Здорово! Можно брать слона?} 18. gxf3 {[%wrong Поищем сильнейший ход.] [%hint Берем слона и не боимся за своего короля.]} (18. Qxd8 $5 {У белых небольшое преимущество, но черные должны добиться ничьей. Поищем сильнейший ход.}) \r\n18... Qxd4 {Отлично! Каким ходом Крамник продолжил атаку?} 19. Nb5 {[%wrong Поищем сильнейший ход.] [%hint Нападем на черного ферзя и пешку a7 одновременно.]} (19. Rcd1 $2 Qh4 {У черных хорошая позиция. Поищем сильнейший ход.}) (19. Qe3 $2 Qb4 {У черных хорошая позиция. Поищем сильнейший ход.}) (19. Ne4 $2 Nxe4 {У черных хорошая позиция. Поищем сильнейший ход.}) \r\n19... Qxb2 {Блестящая игра! Последний ход Каспарова допускает комбинационный удар. Как Крамник продолжил атаку?} 20. Rxc8 {[%wrong Поищем сильнейший ход.] [%hint Разменяем фигуры, чтобы ослабить защиту последней горизонтали.]} Rxc8 {Здорово! Как напасть на черную ладью?} 21. Nd6 {[%wrong У черных приемлемая  позиция. Попробуем снова.] [%hint Централизуем коня с нападением на вражескую фигуру.]} (21. Qxa7 $2 Qxb5 {Черные выигрывают. Попробуем снова.}) (21. Nxa7 $2 Rc2 {У черных хорошая позиция. Попробуем снова.}) \r\n21... Rb8 {Молодец! Как оттеснить короля черных на невыгодную позицию?} 22. Nf7+ {[%wrong Поищем сильнейший ход.] [%hint Оттесним черного короля.]} (22. Ne8 $5 {Это хороший ход, но Крамник находит другой путь к победе. Какой?}) (22. Qc7 $5 {Это хороший ход, но Крамник находит другой путь к победе. Какой?}) (22. Qxa7 $2 Rf8 {У белых небольшое преимущество. Поищем сильнейший ход.}) \r\n22... Kg8 {Прекрасный замысел! Как использовать уязвимое положение черного короля на диагонали a2-g8?} 23. Qe6 {[%wrong Поищем сильнейший ход.] [%hint Подготовим вскрытый шах.]} (23. Ng5 $2 h6 {У черных хорошая позиция. Попробуем снова.}) (23. Nd8 $2 h6 {У черных хорошая позиция. Попробуем снова.}) \r\n23... Rf8 {Отлично! Как использовать уязвимое положение черного короля?} 24. Nd8+ {[%wrong Поищем сильнейший ход.] [%hint Дайте вскрытый шах, чтобы перекрыть последнюю горизонталь, и черной ладье было некуда отступить.]} (24. Nd6+ $5 {Белые выигрывают и после этого хода, но Крамник решил перекрыть последнюю горизонталь конем.}) (24. Nh6+ $5 {Белые выигрывают, но им нужно проявить осторожность. Qg8+ не ведет к спертому мату, потому что черные могут брать конем. Какой ход сделал Крамник?}) (24. Ne5+ $5 {Белые выигрывают, но Крамник решил перекрыть последнюю горизонталь конем. Каким ходом?}) (24. Ng5+ $5 {Белые выигрывают, но Крамник решил перекрыть последнюю горизонталь конем. Каким ходом?}) \r\n24... Kh8 {Молодец! Каким ходом Крамник вынудил чемпиона мира Гарри Каспарова сдаться?} 25. Qe7 {[%wrong Поищем сильнейший ход.] [%hint Нападем на черную ладью.]} (25. Nf7+ $5 {Этот ход не упускает победу, но белым незачем повторять ходы. Поищем кратчайший путь к победе.}) (25. Qd6 $5 {Это хороший ход, но Крамник нашел другой способ атаковать ладью черных. Как он сыграл?}) \r\n25... Rg8 {Отличный ход! Черные сдались, потому что они не могут защитить ладью и помешать мату. Как выигрывают белые после Лg8?} 26. Nf7# {[%wrong Этот ход не ведет к мату. Попробуем снова!] [%hint Поищем мат.] Великолепно! Крамник выиграл вторую партию в матче на первенство мира и довел его до победы со счетом 8.5 - 6.5.} 1-0"
   ],
   "title" : "Сыграй как Владимир Крамник: Крамник против Каспарова",
   "url" : "https://www.chess.com/ru/lessons/sygrai-kak-vladimir-kramnik/sygrai-kak-vladimir-kramnik-kramnik-protiv-kasparova",
   "video" : null
}
