{
   "description" : "Мы уже видели, как Капабланка управлялся с конем - он делал это превосходно. И все же, чемпион мира считал, что слоны сильнее коней (по его словам, в 90 % случаев) и использовал их еще эффективнее! Эта позиция встретилась в партии Хосе-Рауль Капабланка - Джордж Алан Томас на турнире в Гастингсе в 1929 году.",
   "duration" : null,
   "fen" : "1kb5/2pn4/1p1p2p1/p4pBp/2PP4/PPK2P2/4B1PP/8 w - - 0 28",
   "id" : "e7677b88-e225-11e9-bced-4bd8a2c7157b",
   "membership" : 50,
   "questions" : [
      "[Event \"?\"]\r\n[Site \"?\"]\r\n[Date \"????.??.??\"]\r\n[Round \"?\"]\r\n[White \"?\"]\r\n[Black \"?\"]\r\n[Result \"*\"]\r\n[WhiteElo \"\"]\r\n[BlackElo \"\"]\r\n[ECO \"\"]\r\n[FEN \"1kb5/2pn4/1p1p2p1/p4pBp/2PP4/PPK2P2/4B1PP/8 w - - 0 28\"]\r\n[SetUp \"1\"]\r\n{У белых больше пространства и пара слонов, но чтобы выиграть, им нужно правильно ими распорядиться.}\r\n1.Be7\r\n    {[%wrong Этот ход не позволяет ограничить коня черных.] [%hint Ищем ход, позволяющий полностью парализовать позицию черных.] Конь обездвижен, поскольку ему некуда отступить, но это еще не все - все фигуры черных парализованы, потому что конь неподвижен. \r\nВ партии Томас распознал опасность и принял тяжелое решение сразу пожертвовать пешку ходом 28...b5} (1.b4? {В подобной позиции захват пространства на ферзевом фланге - хорошая идея, но у белых есть намного более сильный ход! Посмотрим, можете ли вы ограничить активность фигур противника.}) (1.Bd3? {Этот ход усиливает позицию вашего слона, но у белых есть и намного более сильное продолжение--поищите, как усилить позицию одного из своих слонов, ограничив активность противника.}) (1.g4? {Вы на верном пути, но сейчас у белых есть намного более сильное продолжение. Помешаем фигурам противника активизироваться.}) \r\n*",
      "[Event \"?\"]\r\n[Site \"?\"]\r\n[Date \"????.??.??\"]\r\n[Round \"?\"]\r\n[White \"?\"]\r\n[Black \"?\"]\r\n[Result \"*\"]\r\n[WhiteElo \"\"]\r\n[BlackElo \"\"]\r\n[ECO \"\"]\r\n[FEN \"1k6/1bpnB3/1p1p2p1/p4p1p/2PP4/PPK2P2/4B1PP/8 w - - 2 29\"]\r\n[SetUp \"1\"]\r\n{Если черные играют пассивно, мы сможем использовать преимущество двух слонов, вскрыв позицию и создав мишень для атаки на королевском фланге.}\r\n1.g4\r\n    {[%wrong Этот ход недостаточно точен. Нам нужно вскрыть позицию, пока черные не успели активизировать фигуры] [%hint Попробуем добраться до пешки g6.] Отличная техника! Пока фигуры черных находятся на ферзевом фланге, успевают вскрыть позицию и выиграть пешку с помощью мощных слонов.} (1.b4!? $5 {Неплохой ход. Белым выгодно усилить позицию на ферзевом фланге.}) (1.h4!? $5 {И далее g2-g4 также ведет к прорыву.}) \r\n*",
      "[Event \"?\"]\r\n[Site \"?\"]\r\n[Date \"????.??.??\"]\r\n[Round \"?\"]\r\n[White \"?\"]\r\n[Black \"?\"]\r\n[Result \"*\"]\r\n[SetUp \"1\"]\r\n[FEN \"1k6/1bpnB3/1p1p2p1/p4p2/2PP2p1/PPK2P2/4B2P/8 w - - 0 30\"]\r\n[PlyCount \"1\"]\r\n{Поищем сильнейший ход} \r\n30. fxg4 {[%hint Отыграем пешку.]} *",
      "[Event \"?\"]\r\n[Site \"?\"]\r\n[Date \"????.??.??\"]\r\n[Round \"?\"]\r\n[White \"?\"]\r\n[Black \"?\"]\r\n[Result \"*\"]\r\n[SetUp \"1\"]\r\n[FEN \"1k6/1bpnB3/1p1p2p1/p7/2PP2p1/PPK5/4B2P/8 w - - 0 31\"]\r\n[PlyCount \"1\"]\r\n{Поищем сильнейший ход} \r\n31. Bxg4 {[%hint Отыграем пешку.]} *",
      "[Event \"?\"]\r\n[Site \"?\"]\r\n[Date \"????.??.??\"]\r\n[Round \"?\"]\r\n[White \"?\"]\r\n[Black \"?\"]\r\n[Result \"*\"]\r\n[SetUp \"1\"]\r\n[FEN \"1kb5/2pnB3/1p1p2p1/p7/2PP2B1/PPK5/7P/8 w - - 0 32\"]\r\n[PlyCount \"1\"]\r\n\r\n{Белые вскрыли королевский фланг. Что делать дальше?} \r\n32. Be2 {[%wrong Этот ход не ведет к выигрышу пешки g6!] [%hint Пора использовать слонов и добраться до пешки  g6.] Один слон нападает на пешку \"g\", а другой мешает ее продвижению.} (32. b4 $2 axb4+ {Теперь конь черных войдет в игру после 33.axb4 b5!}) (32. Kd2 $2 Ne5! {Это осложняет вашу задачу после 33.Bxc8 Nc6 34.Bxd6 cxd6 35.Bd7 Nxd4})\r\n(32. Kd3 $2 Ne5+! {На доске ничья!}) (32. Bf3 $2 {На это следует 32...Сb7}) (32. Bd1 $5 {И далее Сd1-c2 тоже выигрывает.}) *",
      "[Event \"?\"]\r\n[Site \"?\"]\r\n[Date \"????.??.??\"]\r\n[Round \"?\"]\r\n[White \"?\"]\r\n[Black \"?\"]\r\n[Result \"*\"]\r\n[WhiteElo \"\"]\r\n[BlackElo \"\"]\r\n[ECO \"\"]\r\n[FEN \"1k6/1bpnB3/1p1p2p1/p7/2PP4/PPK5/4B2P/8 w - - 4 33\"]\r\n[SetUp \"1\"]\r\n{Остается нанести решающий удар, и остальное будет делом техники!}\r\n1.Bd3\r\n    {[%wrong Вы можете вынудить немедленную сдачу.] [%hint Как добиться успеха на королевском фланге?] Триумф стратегии белых. Проходная пешка \"h\" решит исход партии.} \r\n*"
   ],
   "title" : "Слоны Капабланки",
   "url" : "https://www.chess.com/ru/lessons/sekrety-endshpilia-s-kapablankoi/slony-kapablanki",
   "video" : null
}
